gray_swan_ai/__init__.py
gray_swan_ai/_base_client.py
gray_swan_ai/_client.py
gray_swan_ai/_compat.py
gray_swan_ai/_constants.py
gray_swan_ai/_exceptions.py
gray_swan_ai/_files.py
gray_swan_ai/_models.py
gray_swan_ai/_qs.py
gray_swan_ai/_resource.py
gray_swan_ai/_response.py
gray_swan_ai/_streaming.py
gray_swan_ai/_types.py
gray_swan_ai/_version.py
gray_swan_ai/py.typed
gray_swan_ai/_utils/__init__.py
gray_swan_ai/_utils/_logs.py
gray_swan_ai/_utils/_proxy.py
gray_swan_ai/_utils/_reflection.py
gray_swan_ai/_utils/_streams.py
gray_swan_ai/_utils/_sync.py
gray_swan_ai/_utils/_transform.py
gray_swan_ai/_utils/_typing.py
gray_swan_ai/_utils/_utils.py
gray_swan_ai/resources/__init__.py
gray_swan_ai/resources/moderation.py
gray_swan_ai/resources/chat/__init__.py
gray_swan_ai/resources/chat/chat.py
gray_swan_ai/resources/chat/completion.py
gray_swan_ai/types/__init__.py
gray_swan_ai/types/create_moderation_response.py
gray_swan_ai/types/moderation_create_params.py
gray_swan_ai/types/chat/__init__.py
gray_swan_ai/types/chat/chat_completion_choice.py
gray_swan_ai/types/chat/chat_completion_delta.py
gray_swan_ai/types/chat/chat_completion_delta_tool_call.py
gray_swan_ai/types/chat/chat_completion_delta_tool_call_function.py
gray_swan_ai/types/chat/chat_completion_message.py
gray_swan_ai/types/chat/chat_completion_stream_choice.py
gray_swan_ai/types/chat/chat_completion_tool_call.py
gray_swan_ai/types/chat/chat_completion_tool_call_function.py
gray_swan_ai/types/chat/completion_create_params.py
gray_swan_ai/types/chat/completion_create_response.py
gray_swan_ai/types/chat/create_chat_completion_response.py
gray_swan_ai/types/chat/create_chat_completion_stream_response.py
grayswan_api-0.1.0a48.dist-info/METADATA
grayswan_api-0.1.0a48.dist-info/WHEEL
grayswan_api-0.1.0a48.dist-info/licenses/LICENSE
grayswan_api-0.1.0a48.dist-info/RECORD
